rj_ml_utils/Constants.py
rj_ml_utils/__init__.py
rj_ml_utils/feature_selection.py
rj_ml_utils/metrics.py
rj_ml_utils/package/__init__.py
rj_ml_utils/package/details.py
rj_ml_utils-1.0.0.dist-info/LICENSE
rj_ml_utils-1.0.0.dist-info/METADATA
rj_ml_utils-1.0.0.dist-info/WHEEL
rj_ml_utils-1.0.0.dist-info/top_level.txt
rj_ml_utils-1.0.0.dist-info/RECORD
