Metadata-Version: 2.1
Name: rj-ml-utils
Version: 1.0.0
Summary: Utility package for ML
Home-page: https://github.com/raghavajoijode/rj-ml-utils
Author: Raghava Joijode
Author-email: raghava.joijode@gmail.com
License: UNKNOWN
Platform: UNKNOWN
Classifier: Programming Language :: Python :: 3
Classifier: License :: OSI Approved :: MIT License
Classifier: Operating System :: OS Independent
Requires-Python: >=3.6
Requires-Dist: numpy (==1.18.5)
Requires-Dist: scikit-learn (==0.23.2)
